odoo9_addon_mail_cleanup-9.0.1.0.0-py2.7-nspkg.pth
odoo9_addon_mail_cleanup-9.0.1.0.0.dist-info/top_level.txt
odoo9_addon_mail_cleanup-9.0.1.0.0.dist-info/WHEEL
odoo9_addon_mail_cleanup-9.0.1.0.0.dist-info/RECORD
odoo9_addon_mail_cleanup-9.0.1.0.0.dist-info/metadata.json
odoo9_addon_mail_cleanup-9.0.1.0.0.dist-info/DESCRIPTION.rst
odoo9_addon_mail_cleanup-9.0.1.0.0.dist-info/METADATA
odoo9_addon_mail_cleanup-9.0.1.0.0.dist-info/namespace_packages.txt
odoo_addons/mail_cleanup/__openerp__.py
odoo_addons/mail_cleanup/__init__.py
odoo_addons/mail_cleanup/README.rst
odoo_addons/mail_cleanup/models/mail_cleanup.py
odoo_addons/mail_cleanup/models/__init__.py
odoo_addons/mail_cleanup/views/mail_view.xml
